pingera_mcp/__init__.py
pingera_mcp/__main__.py
pingera_mcp/auth.py
pingera_mcp/config.py
pingera_mcp/exceptions.py
pingera_mcp/mcp_server.py
pingera_mcp/sdk_client.py
pingera_mcp/resources/__init__.py
pingera_mcp/resources/base.py
pingera_mcp/resources/components.py
pingera_mcp/resources/pages.py
pingera_mcp/resources/status.py
pingera_mcp/tools/__init__.py
pingera_mcp/tools/alerts.py
pingera_mcp/tools/base.py
pingera_mcp/tools/check_groups.py
pingera_mcp/tools/checks.py
pingera_mcp/tools/components.py
pingera_mcp/tools/heartbeats.py
pingera_mcp/tools/incidents.py
pingera_mcp/tools/pages.py
pingera_mcp/tools/playwright_generator.py
pingera_mcp/tools/secrets.py
pingera_mcp/tools/status.py
pingera_mcp_server-0.1.11.dist-info/METADATA
pingera_mcp_server-0.1.11.dist-info/WHEEL
pingera_mcp_server-0.1.11.dist-info/licenses/LICENSE
pingera_mcp_server-0.1.11.dist-info/RECORD
