Metadata-Version: 2.4
Name: pingera-mcp-server
Version: 0.1.11
Summary: Model Context Protocol (MCP) server for Pingera monitoring service integration
Project-URL: Homepage, https://pingera.ru
Project-URL: Documentation, https://github.com/pingera/pingera-mcp#readme
Project-URL: Repository, https://github.com/pingera/pingera-mcp
Project-URL: Issues, https://github.com/pingera/pingera-mcp/issues
Project-URL: Changelog, https://github.com/pingera/pingera-mcp/blob/main/CHANGELOG.md
Author-email: Pingera Team <privet@pingera.ru>
Maintainer-email: Pingera Team <privet@pingera.ru>
License: 
License-File: LICENSE
Keywords: api,mcp,monitoring,pingera,playwright,security,statuspage,synthetic,web monitoring
Classifier: Development Status :: 4 - Beta
Classifier: Intended Audience :: Developers
Classifier: License :: OSI Approved :: MIT License
Classifier: Operating System :: OS Independent
Classifier: Programming Language :: Python :: 3
Classifier: Programming Language :: Python :: 3.10
Classifier: Programming Language :: Python :: 3.11
Classifier: Programming Language :: Python :: 3.12
Classifier: Topic :: Communications
Classifier: Topic :: Internet :: WWW/HTTP
Classifier: Topic :: Software Development :: Libraries :: Python Modules
Classifier: Topic :: System :: Monitoring
Classifier: Topic :: System :: Systems Administration
Requires-Python: >=3.10
Requires-Dist: fastmcp>=2.11.2
Requires-Dist: google-generativeai>=0.8.5
Requires-Dist: mcp>=1.2.0
Requires-Dist: pingera-sdk>=1.0.10
Requires-Dist: pydantic>=2.0.0
Requires-Dist: pytest-cov>=6.2.1
Requires-Dist: python-dotenv>=1.0.0
Requires-Dist: requests>=2.31.0
Requires-Dist: sift-stack-py>=0.8.3
Requires-Dist: urllib3>=2.5.0
Provides-Extra: dev
Requires-Dist: black>=23.0.0; extra == 'dev'
Requires-Dist: isort>=5.12.0; extra == 'dev'
Requires-Dist: mypy>=1.5.0; extra == 'dev'
Requires-Dist: pytest-asyncio>=0.21.0; extra == 'dev'
Requires-Dist: pytest-cov>=4.0.0; extra == 'dev'
Requires-Dist: pytest-mock>=3.10.0; extra == 'dev'
Requires-Dist: pytest>=7.0.0; extra == 'dev'
